setup.py
django_timezones2.egg-info/PKG-INFO
django_timezones2.egg-info/SOURCES.txt
django_timezones2.egg-info/dependency_links.txt
django_timezones2.egg-info/requires.txt
django_timezones2.egg-info/top_level.txt
django_timezones2.egg-info/zip-safe
timezones2/__init__.py
timezones2/forms.py
timezones2/middleware.py
timezones2/models.py
timezones2/tests.py
timezones2/utils.py
timezones2/views.py
timezones2/zones.py
timezones2/templatetags/__init__.py
timezones2/templatetags/tz2_tags.py