Metadata-Version: 1.1
Name: django-timezones2
Version: 1.0.4
Summary: Timezone utilities for Django
Home-page: https://bitbucket.org/sayane/django-timezones2
Author: Rafal Stozek
Author-email: say4ne@gmail.com
License: Beer-ware
Platform: UNKNOWN
Classifier: Framework :: Django
Classifier: Environment :: Web Environment
Classifier: Intended Audience :: Developers
Classifier: Development Status :: 5 - Production/Stable
Requires: pytz
